jdk4py/__init__.py
jdk4py/_added_modules.py
jdk4py/_included_locales.py
jdk4py/java-runtime/bin/api-ms-win-core-console-l1-1-0.dll
jdk4py/java-runtime/bin/api-ms-win-core-console-l1-2-0.dll
jdk4py/java-runtime/bin/api-ms-win-core-datetime-l1-1-0.dll
jdk4py/java-runtime/bin/api-ms-win-core-debug-l1-1-0.dll
jdk4py/java-runtime/bin/api-ms-win-core-errorhandling-l1-1-0.dll
jdk4py/java-runtime/bin/api-ms-win-core-fibers-l1-1-0.dll
jdk4py/java-runtime/bin/api-ms-win-core-fibers-l1-1-1.dll
jdk4py/java-runtime/bin/api-ms-win-core-file-l1-1-0.dll
jdk4py/java-runtime/bin/api-ms-win-core-file-l1-2-0.dll
jdk4py/java-runtime/bin/api-ms-win-core-file-l2-1-0.dll
jdk4py/java-runtime/bin/api-ms-win-core-handle-l1-1-0.dll
jdk4py/java-runtime/bin/api-ms-win-core-heap-l1-1-0.dll
jdk4py/java-runtime/bin/api-ms-win-core-interlocked-l1-1-0.dll
jdk4py/java-runtime/bin/api-ms-win-core-kernel32-legacy-l1-1-1.dll
jdk4py/java-runtime/bin/api-ms-win-core-libraryloader-l1-1-0.dll
jdk4py/java-runtime/bin/api-ms-win-core-localization-l1-2-0.dll
jdk4py/java-runtime/bin/api-ms-win-core-memory-l1-1-0.dll
jdk4py/java-runtime/bin/api-ms-win-core-namedpipe-l1-1-0.dll
jdk4py/java-runtime/bin/api-ms-win-core-processenvironment-l1-1-0.dll
jdk4py/java-runtime/bin/api-ms-win-core-processthreads-l1-1-0.dll
jdk4py/java-runtime/bin/api-ms-win-core-processthreads-l1-1-1.dll
jdk4py/java-runtime/bin/api-ms-win-core-profile-l1-1-0.dll
jdk4py/java-runtime/bin/api-ms-win-core-rtlsupport-l1-1-0.dll
jdk4py/java-runtime/bin/api-ms-win-core-string-l1-1-0.dll
jdk4py/java-runtime/bin/api-ms-win-core-synch-l1-1-0.dll
jdk4py/java-runtime/bin/api-ms-win-core-synch-l1-2-0.dll
jdk4py/java-runtime/bin/api-ms-win-core-sysinfo-l1-1-0.dll
jdk4py/java-runtime/bin/api-ms-win-core-sysinfo-l1-2-0.dll
jdk4py/java-runtime/bin/api-ms-win-core-timezone-l1-1-0.dll
jdk4py/java-runtime/bin/api-ms-win-core-util-l1-1-0.dll
jdk4py/java-runtime/bin/api-ms-win-crt-conio-l1-1-0.dll
jdk4py/java-runtime/bin/api-ms-win-crt-convert-l1-1-0.dll
jdk4py-21.0.8.0.dist-info/WHEEL
jdk4py-21.0.8.0.dist-info/METADATA
jdk4py-21.0.8.0.dist-info/RECORD
