Metadata-Version: 2.3
Name: jdk4py
Version: 21.0.8.0
Summary: A JDK shipped in a Python package
Keywords: jdk,java,jvm,jre
Author: ActiveViam
Author-email: ActiveViam <dev@atoti.io>
Classifier: Development Status :: 5 - Production/Stable
Classifier: License :: OSI Approved :: GNU General Public License v2 (GPLv2)
Classifier: Operating System :: MacOS
Classifier: Operating System :: Microsoft :: Windows
Classifier: Operating System :: POSIX :: Linux
Classifier: Programming Language :: Python :: 3
Requires-Python: >=3.10
Project-URL: Repository, https://github.com/activeviam/jdk4py
